[
{"type":"header","version":"4.9.0.1","comment":"Export to JSON plugin for PHPMyAdmin"},
{"type":"database","name":"if0_36252759_recall_db"},
{"type":"table","name":"campanhas_recall","database":"if0_36252759_recall_db","data":
[
{"id":"1","data_inicio":"2017-05-29","data_fim_campanha":null,"titulo":"Fogões Coliseum","fornecedor":"ATLAS INDÚSTRIA DE ELETRODOMÉSTICOS LTDA.","tipo_risco":"Cortes\/Ferimentos","pais_origem":"Brasil","produto":"Fogões Coliseum","total_afetado":"32817","total_atendido":"0"},
{"id":"2","data_inicio":"2017-06-20","data_fim_campanha":null,"titulo":"Fogões Top Machine","fornecedor":"ATLAS INDÚSTRIA DE ELETRODOMÉSTICOS LTDA.","tipo_risco":"Envenenamento\/Intoxicação","pais_origem":"Brasil","produto":"Fogões Top Machine","total_afetado":"4048","total_atendido":"0"},
{"id":"3","data_inicio":"2017-03-22","data_fim_campanha":"2018-06-13","titulo":"Audi A4 Sedan 2.0","fornecedor":"Audi do Brasil Indústria e Comércio de Veículos Ltda. ","tipo_risco":"Não funcionamento adequado do produto","pais_origem":"Brasil","produto":"Audi A4","total_afetado":"7","total_atendido":"7"},
{"id":"4","data_inicio":"2017-03-22","data_fim_campanha":null,"titulo":"A4 Avant, A4 Sedã, A5 Cabriolet, A5 Coupé e A5 Sportback","fornecedor":"Audi do Brasil Indústria e Comércio de Veículos Ltda. ","tipo_risco":"Incêndio","pais_origem":"Brasil","produto":"A4 Avant, A4 Sedã, A5 Cabriolet, A5 Coupé e A5 Sportback ","total_afetado":"5570","total_atendido":"1772"},
{"id":"5","data_inicio":"2017-04-25","data_fim_campanha":null,"titulo":"Audi A3","fornecedor":"Audi do Brasil Indústria e Comércio de Veículos Ltda. ","tipo_risco":"Não funcionamento adequado do produto","pais_origem":"Brasil","produto":"Audi A3","total_afetado":"526","total_atendido":"132"},
{"id":"6","data_inicio":"2017-04-25","data_fim_campanha":null,"titulo":"Q5 2.0 e SQ5 3.0","fornecedor":"Audi do Brasil Indústria e Comércio de Veículos Ltda. ","tipo_risco":"Não funcionamento adequado do produto","pais_origem":"Brasil","produto":"Q5 2.0 e SQ5 3.0","total_afetado":"2395","total_atendido":"1370"},
{"id":"7","data_inicio":"2017-07-25","data_fim_campanha":null,"titulo":"Q3 e RSQ3","fornecedor":"Audi do Brasil Indústria e Comércio de Veículos Ltda. ","tipo_risco":"Não funcionamento adequado do produto","pais_origem":"Brasil","produto":"Q3 e RSQ3","total_afetado":"3568","total_atendido":"2497"},
{"id":"8","data_inicio":"2017-01-05","data_fim_campanha":null,"titulo":"BMW, 420i Cabrio Sport GP; 428i Cabrio; X3 xDrive20i; X Line e X4 xDrive35i M Sport,","fornecedor":"BMW do Brasil Ltda.","tipo_risco":"Cortes\/Ferimentos","pais_origem":"Alemanha","produto":"BMW 420i Cabrio 428i Cabrio; X3 xDrive20i; X Line e 4 xDrive35i","total_afetado":"5","total_atendido":"1"},
{"id":"9","data_inicio":"2017-01-09","data_fim_campanha":null,"titulo":"BMW 430i Cabrio Sport Limited Edition","fornecedor":"BMW do Brasil Ltda.","tipo_risco":"Não funcionamento adequado do produto","pais_origem":"Alemanha","produto":"BMW 430i Cabrio Sport Limited Edition","total_afetado":"1","total_atendido":"0"},
{"id":"10","data_inicio":"2017-02-08","data_fim_campanha":"2018-06-15","titulo":"BMW, modelo 750i","fornecedor":"BMW do Brasil Ltda.","tipo_risco":"Cortes\/Ferimentos","pais_origem":"Brasil","produto":"BMW 750i","total_afetado":"1","total_atendido":"1"},
{"id":"11","data_inicio":"2017-03-27","data_fim_campanha":null,"titulo":"BMW 320i, BMW 323i, BMW 325i, BMW 325i Coupé, BMW 330i, BMW 330i Cabrio, BMW 525i, 530i, BMW 540i, BMW 540i M Sport, BMW M3, BMW M5, BMW X5 3.0i, BMW X5 4.4i","fornecedor":"BMW do Brasil Ltda.","tipo_risco":"Cortes\/Ferimentos","pais_origem":"Alemanha","produto":"BMW 320i, 323i, 325i, 325 Coupé, 330i, 330i Cabrio, 525i, 530i, 540i, 540i M Sport, M3, M5, X5 3.0i, X5 4.4i.","total_afetado":"2406","total_atendido":"89"},
{"id":"12","data_inicio":"2017-04-07","data_fim_campanha":null,"titulo":"X1 sDrive20i X Line","fornecedor":"BMW do Brasil Ltda.","tipo_risco":"Cortes\/Ferimentos","pais_origem":"Alemanha","produto":"X1 sDrive20i X Line","total_afetado":"23","total_atendido":"19"},
{"id":"13","data_inicio":"2017-04-10","data_fim_campanha":null,"titulo":"i3 REX Entry e i3 REX Full","fornecedor":"BMW do Brasil Ltda.","tipo_risco":"Fogo","pais_origem":"Alemanha","produto":"i3 REX Entry e i3 REX Full","total_afetado":"178","total_atendido":"137"},
{"id":"14","data_inicio":"2017-04-17","data_fim_campanha":null,"titulo":"135i Coupé MSport, 335i Cabrio M Sport, 335i M Sport, 535i GT, 535i M Sport, M Coupé e Z4 35i","fornecedor":"BMW do Brasil Ltda.","tipo_risco":"Cortes\/Ferimentos","pais_origem":"Alemanha","produto":"135i Coupé MSport, 335i Cabrio M Sport, 335i M Sport, 535i GT, 535i M Sport, M Coupé e Z4 35i","total_afetado":"152","total_atendido":"0"},
{"id":"15","data_inicio":"2017-07-31","data_fim_campanha":null,"titulo":"R1200 GS e R1200 GS Adventure","fornecedor":"BMW do Brasil Ltda.","tipo_risco":"Cortes\/Ferimentos","pais_origem":"Alemanha","produto":"R1200 GS e R1200 GS Adventure","total_afetado":"8077","total_atendido":"5818"},
{"id":"16","data_inicio":"2017-09-06","data_fim_campanha":null,"titulo":"BMW R Nine T","fornecedor":"BMW do Brasil Ltda.","tipo_risco":"Cortes\/Ferimentos","pais_origem":"Alemanha","produto":"BMW R Nine T","total_afetado":"222","total_atendido":"92"},
{"id":"17","data_inicio":"2017-11-10","data_fim_campanha":"2018-05-29","titulo":"BMW X3 3.0si Sport","fornecedor":"BMW do Brasil Ltda.","tipo_risco":"Cortes\/Ferimentos","pais_origem":"Alemanha","produto":"BMW X3 3.0Si Sport","total_afetado":"1","total_atendido":"1"},
{"id":"18","data_inicio":"2017-01-09","data_fim_campanha":null,"titulo":"Subaru Forester 2.5L Turbo","fornecedor":"CAOA MONTADORA DE VEÍCULOS LTDA.","tipo_risco":"Incêndio","pais_origem":"Japão","produto":"Subaru Forester 2.5L Turbo","total_afetado":"120","total_atendido":"67"},
{"id":"19","data_inicio":"2017-01-10","data_fim_campanha":null,"titulo":"Subaru Legacy 2.0, Impreza WRX, STI e Forester Turbo","fornecedor":"CAOA MONTADORA DE VEÍCULOS LTDA.","tipo_risco":"Fogo","pais_origem":"Japão","produto":"Subaru Legacy, Impreza WRX, STI e Forester Turbo","total_afetado":"1928","total_atendido":"0"},
{"id":"20","data_inicio":"2017-05-31","data_fim_campanha":null,"titulo":"Subaru Legacy, Outback, Tribeca, Forester e Impreza, WRX e STI","fornecedor":"CAOA MONTADORA DE VEÍCULOS LTDA.","tipo_risco":"Não funcionamento adequado do produto","pais_origem":"Japão","produto":"Subaru Legacy, Outback, Tribeca, Forester e Impreza, WRX e STI","total_afetado":"1457","total_atendido":"0"},
{"id":"21","data_inicio":"2017-02-06","data_fim_campanha":null,"titulo":"Ducati Scrambler","fornecedor":"DUCATI DO BRASIL INDÚSTRIA E COMÉRCIO DE MOTOCICLETAS LTDA","tipo_risco":"Não funcionamento adequado do produto","pais_origem":"Itália","produto":"Ducati Scrambler","total_afetado":"326","total_atendido":"182"},
{"id":"22","data_inicio":"2017-01-12","data_fim_campanha":null,"titulo":"Veículos Jeep Wrangler","fornecedor":"FCA - FIAT CHRYSLER AUTOMÓVEIS BRASIL LTDA.","tipo_risco":"Cortes\/Ferimentos","pais_origem":"Estados Unidos","produto":"Jeep Wrangler","total_afetado":"18","total_atendido":"0"},
{"id":"23","data_inicio":"2017-04-03","data_fim_campanha":null,"titulo":"Jeep Compass e Fiat Toro","fornecedor":"FCA - FIAT CHRYSLER AUTOMÓVEIS BRASIL LTDA.","tipo_risco":"Cortes\/Ferimentos","pais_origem":"Brasil","produto":"Jeep Compass | Toro","total_afetado":"10486","total_atendido":"0"},
{"id":"24","data_inicio":"2017-04-03","data_fim_campanha":null,"titulo":"Fiat Uno Firefly e Fiat Strada, ano\/modelo 2016\/2017","fornecedor":"FCA - FIAT CHRYSLER AUTOMÓVEIS BRASIL LTDA.","tipo_risco":"Cortes\/Ferimentos","pais_origem":"Brasil","produto":" Fiat Uno Firefly e Fiat Strada | Fiat Uno Firefly e Fiat Strada.","total_afetado":"17111","total_atendido":"0"},
{"id":"25","data_inicio":"2017-05-24","data_fim_campanha":null,"titulo":"Bravo, Doblò, Doblò Furgão, Fiorino, Grand Siena, Idea, Linea, Novo Palio, Palio Fire, Palio Weekend, Siena, Strada e Uno","fornecedor":"FCA - FIAT CHRYSLER AUTOMÓVEIS BRASIL LTDA.","tipo_risco":"Cortes\/Ferimentos","pais_origem":"Brasil","produto":"Bravo, Doblò, Doblò Furgão, Fiorino, Grand Siena, Idea, Linea, Novo Palio, Palio Fire, Palio Weekend, Siena, Strada e Uno","total_afetado":"70740","total_atendido":"0"},
{"id":"26","data_inicio":"2017-06-26","data_fim_campanha":null,"titulo":"Jeep Renegade","fornecedor":"FCA - FIAT CHRYSLER AUTOMÓVEIS BRASIL LTDA.","tipo_risco":"Cortes\/Ferimentos","pais_origem":"Brasil","produto":"Jeep Renegade","total_afetado":"88957","total_atendido":"0"},
{"id":"27","data_inicio":"2017-08-31","data_fim_campanha":null,"titulo":"Chrysler 300, Dodge Charge, Dodge Durango e Jeep Grand Cherokee","fornecedor":"FCA - FIAT CHRYSLER AUTOMÓVEIS BRASIL LTDA.","tipo_risco":"Fogo","pais_origem":"Estados Unidos","produto":"Chrysler 300 | Dodge Durango | Grand Cherokee | Dodge Charger","total_afetado":"3908","total_atendido":"0"},
{"id":"28","data_inicio":"2017-09-25","data_fim_campanha":null,"titulo":"Fiat Freemont e Dodge Journey","fornecedor":"FCA - FIAT CHRYSLER AUTOMÓVEIS BRASIL LTDA.","tipo_risco":"Cortes\/Ferimentos","pais_origem":"México","produto":"Freemont | Dodge Journey ","total_afetado":"33983","total_atendido":"0"},
{"id":"29","data_inicio":"2017-10-09","data_fim_campanha":null,"titulo":"Toro","fornecedor":"FCA - FIAT CHRYSLER AUTOMÓVEIS BRASIL LTDA.","tipo_risco":"Cortes\/Ferimentos","pais_origem":"Brasil","produto":"Toro ","total_afetado":"223","total_atendido":"0"},
{"id":"30","data_inicio":"2017-10-09","data_fim_campanha":null,"titulo":"Novo Palio, Palio Weekend, Palio Fire, Uno, Grand Siena, Fiorino, Strada e Mobi","fornecedor":"FCA - FIAT CHRYSLER AUTOMÓVEIS BRASIL LTDA.","tipo_risco":"Cortes\/Ferimentos","pais_origem":"Brasil","produto":"Novo Palio, Palio Weekend, Palio Fire, Uno, Grand Siena, Fiorino, Strada e Mobi","total_afetado":"195","total_atendido":"0"},
{"id":"31","data_inicio":"2017-11-01","data_fim_campanha":null,"titulo":"Fiat Picape RAM 2500","fornecedor":"FCA - FIAT CHRYSLER AUTOMÓVEIS BRASIL LTDA.","tipo_risco":"Fogo","pais_origem":"Estados Unidos","produto":"Picape RAM 2500","total_afetado":"829","total_atendido":"0"},
{"id":"32","data_inicio":"2017-11-13","data_fim_campanha":null,"titulo":"Fiat Punto, Doblo, Uno, Mobi, Pálio Weekend, Strada, Novo Pálio e Grand Siena","fornecedor":"FCA - FIAT CHRYSLER AUTOMÓVEIS BRASIL LTDA.","tipo_risco":"Cortes\/Ferimentos","pais_origem":"Brasil","produto":"Fiat Punto,  Doblo, Uno, Mobi, Palio Weekend  e outros","total_afetado":"5802","total_atendido":"0"},
{"id":"33","data_inicio":"2017-11-13","data_fim_campanha":null,"titulo":"Jeep Grand Cherokee e Dodge Durango","fornecedor":"FCA - FIAT CHRYSLER AUTOMÓVEIS BRASIL LTDA.","tipo_risco":"Cortes\/Ferimentos","pais_origem":"Estados Unidos","produto":"Fiat Jeep Grand Cherokee e Dodge Durango","total_afetado":"5145","total_atendido":"0"},
{"id":"34","data_inicio":"2017-12-04","data_fim_campanha":null,"titulo":"FCA JEEP RENEGADE","fornecedor":"FCA - FIAT CHRYSLER AUTOMÓVEIS BRASIL LTDA.","tipo_risco":"Cortes\/Ferimentos","pais_origem":"Brasil","produto":"Jeep Renegade","total_afetado":"6537","total_atendido":"0"},
{"id":"35","data_inicio":"2017-12-11","data_fim_campanha":null,"titulo":"Fiat Argo","fornecedor":"FCA - FIAT CHRYSLER AUTOMÓVEIS BRASIL LTDA.","tipo_risco":"Cortes\/Ferimentos","pais_origem":"Brasil","produto":"Fiat Argo","total_afetado":"21778","total_atendido":"0"},
{"id":"36","data_inicio":"2017-01-20","data_fim_campanha":null,"titulo":"Ford Fusion","fornecedor":"FORD MOTOR COMPANY BRASIL LTDA.","tipo_risco":"Cortes\/Ferimentos","pais_origem":"México","produto":"Ford Fusion","total_afetado":"20020","total_atendido":"4199"},
{"id":"37","data_inicio":"2017-03-02","data_fim_campanha":null,"titulo":"EcoSport, KA e KA+","fornecedor":"FORD MOTOR COMPANY BRASIL LTDA.","tipo_risco":"Cortes\/Ferimentos","pais_origem":"Brasil","produto":"Ford EcoSport, KA e KA+","total_afetado":"9078","total_atendido":"3876"},
{"id":"38","data_inicio":"2017-04-24","data_fim_campanha":null,"titulo":"Ford Edge","fornecedor":"FORD MOTOR COMPANY BRASIL LTDA.","tipo_risco":"Cortes\/Ferimentos","pais_origem":"Canadá","produto":"Ford Edge","total_afetado":"495","total_atendido":"0"},
{"id":"39","data_inicio":"2017-04-26","data_fim_campanha":null,"titulo":"Ford Ranger","fornecedor":"FORD MOTOR COMPANY BRASIL LTDA.","tipo_risco":"Cortes\/Ferimentos","pais_origem":"Argentina","produto":"Ranger","total_afetado":"910","total_atendido":"0"},
{"id":"40","data_inicio":"2017-05-26","data_fim_campanha":null,"titulo":"Ford Ranger 2015 a 2017","fornecedor":"FORD MOTOR COMPANY BRASIL LTDA.","tipo_risco":"Cortes\/Ferimentos","pais_origem":"Argentina","produto":"Ford Ranger 2015 a 2017","total_afetado":"5354","total_atendido":"1238"},
{"id":"41","data_inicio":"2017-07-20","data_fim_campanha":null,"titulo":"Troller T4","fornecedor":"FORD MOTOR COMPANY BRASIL LTDA.","tipo_risco":"Cortes\/Ferimentos","pais_origem":"Brasil","produto":"Troller T4","total_afetado":"3635","total_atendido":"1854"},
{"id":"42","data_inicio":"2017-08-01","data_fim_campanha":null,"titulo":"Ford F-4000","fornecedor":"FORD MOTOR COMPANY BRASIL LTDA.","tipo_risco":"Cortes\/Ferimentos","pais_origem":"Brasil","produto":"Ford F-4000","total_afetado":"160","total_atendido":"85"},
{"id":"43","data_inicio":"2017-08-29","data_fim_campanha":"2018-05-24","titulo":"Ford  Fusion","fornecedor":"FORD MOTOR COMPANY BRASIL LTDA.","tipo_risco":"Cortes\/Ferimentos","pais_origem":"México","produto":"Ford Fusion","total_afetado":"1","total_atendido":"1"},
{"id":"44","data_inicio":"2017-09-04","data_fim_campanha":null,"titulo":"Ford Cargo C-2042 e Ford Cargo C-2842","fornecedor":"FORD MOTOR COMPANY BRASIL LTDA.","tipo_risco":"Cortes\/Ferimentos","pais_origem":"Brasil","produto":"Ford Cargo C-2042 e Ford Cargo C-2842","total_afetado":"1396","total_atendido":"0"},
{"id":"45","data_inicio":"2017-09-20","data_fim_campanha":null,"titulo":"FORD, modelos F-350 e F-4000","fornecedor":"FORD MOTOR COMPANY BRASIL LTDA.","tipo_risco":"Cortes\/Ferimentos","pais_origem":"Brasil","produto":"F-350 e F-4000","total_afetado":"1433","total_atendido":"0"},
{"id":"46","data_inicio":"2017-09-22","data_fim_campanha":null,"titulo":"Ford F-350 e F-4000","fornecedor":"FORD MOTOR COMPANY BRASIL LTDA.","tipo_risco":"Cortes\/Ferimentos","pais_origem":"Brasil","produto":"F-350 e F-4000","total_afetado":"13","total_atendido":"7"},
{"id":"47","data_inicio":"2017-05-19","data_fim_campanha":"2018-06-11","titulo":"Chevrolet Onix Joy","fornecedor":"General Motors do Brasil LTDA.","tipo_risco":"Cortes\/Ferimentos","pais_origem":"Brasil","produto":"Chevrolet Onix Joy","total_afetado":"22","total_atendido":"22"},
{"id":"48","data_inicio":"2017-09-11","data_fim_campanha":null,"titulo":"Chevrolet Spin","fornecedor":"General Motors do Brasil LTDA.","tipo_risco":"Fogo","pais_origem":"Brasil","produto":"Chevrolet Spin","total_afetado":"159696","total_atendido":"0"},
{"id":"49","data_inicio":"2017-01-30","data_fim_campanha":null,"titulo":"Civic, Fit, City e Accord","fornecedor":"Honda Automóveis do Brasil Ltda","tipo_risco":"Não funcionamento adequado do produto","pais_origem":"Brasil","produto":"Civic | Honda Fit | Honda City | Accord ","total_afetado":"34530","total_atendido":"0"},
{"id":"50","data_inicio":"2017-08-30","data_fim_campanha":null,"titulo":"Honda Accord","fornecedor":"Honda Automóveis do Brasil Ltda","tipo_risco":"Incêndio","pais_origem":"Estados Unidos","produto":"Accord","total_afetado":"555","total_atendido":"188"},
{"id":"51","data_inicio":"2017-05-15","data_fim_campanha":null,"titulo":"Pajero Full","fornecedor":"HPE AUTOMOTORES DO BRASIL LTDA ","tipo_risco":"Não funcionamento adequado do produto","pais_origem":"Japão","produto":"Pajero Full","total_afetado":"7826","total_atendido":"2105"},
{"id":"52","data_inicio":"2017-07-10","data_fim_campanha":null,"titulo":"Mitsubishi Outlander Phev","fornecedor":"HPE AUTOMOTORES DO BRASIL LTDA ","tipo_risco":"Cortes\/Ferimentos","pais_origem":"Japão","produto":"Outlander Phev","total_afetado":"59","total_atendido":"51"},
{"id":"53","data_inicio":"2017-10-19","data_fim_campanha":null,"titulo":"Mitsubishi modelo PAJERO FULL","fornecedor":"HPE AUTOMOTORES DO BRASIL LTDA ","tipo_risco":"Cortes\/Ferimentos","pais_origem":"Japão","produto":"Pajero Full","total_afetado":"5972","total_atendido":"1787"},
{"id":"54","data_inicio":"2017-12-11","data_fim_campanha":null,"titulo":"Mitsubishi LANCER, ASX, LANCER EVOLUTION X, OUTLANDER E OUTLANDER PHEV","fornecedor":"HPE AUTOMOTORES DO BRASIL LTDA ","tipo_risco":"Cortes\/Ferimentos","pais_origem":"Brasil","produto":"LANCER, LANCER EVO X, OUTLANDER, OUTLANDER PHEV E ASX","total_afetado":"28420","total_atendido":"16653"},
{"id":"55","data_inicio":"2017-09-01","data_fim_campanha":null,"titulo":"Hyundai Santa Fé e Grand Santa Fé","fornecedor":"HYUNDAI MOTOR BRASIL MONTADORA DE AUTOMÓVEIS DO BRASIL LTDA.","tipo_risco":"Cortes\/Ferimentos","pais_origem":"Coreia do Sul","produto":"Hyundai Santa Fé e Grand Santa Fé","total_afetado":"9752","total_atendido":"0"},
{"id":"56","data_inicio":"2017-10-11","data_fim_campanha":null,"titulo":"Hyundai HB20 e HB20S","fornecedor":"HYUNDAI MOTOR BRASIL MONTADORA DE AUTOMÓVEIS DO BRASIL LTDA.","tipo_risco":"Cortes\/Ferimentos","pais_origem":"Brasil","produto":"Hyundai HB20 e HB20S","total_afetado":"3109","total_atendido":"1312"},
{"id":"57","data_inicio":"2017-03-10","data_fim_campanha":null,"titulo":"Jaguar XF 2.0L GTDi","fornecedor":"Jaguar e Land Rover Brasil Importação e Comércio de Veículos LTDA.","tipo_risco":"Fogo","pais_origem":"Reino Unido","produto":"Jaguar XF 2.0L GTDi","total_afetado":"619","total_atendido":"400"},
{"id":"58","data_inicio":"2017-03-13","data_fim_campanha":null,"titulo":"Land Rover Sport","fornecedor":"Jaguar e Land Rover Brasil Importação e Comércio de Veículos LTDA.","tipo_risco":"Cortes\/Ferimentos","pais_origem":"Reino Unido","produto":"Land Rover, modelo Land Rover Sport","total_afetado":"1","total_atendido":"0"},
{"id":"59","data_inicio":"2017-04-27","data_fim_campanha":null,"titulo":"Jaguar XE e F-Type","fornecedor":"Jaguar e Land Rover Brasil Importação e Comércio de Veículos LTDA.","tipo_risco":"Cortes\/Ferimentos","pais_origem":"Reino Unido","produto":"Jaguar XE e F-Type","total_afetado":"197","total_atendido":"160"},
{"id":"60","data_inicio":"2017-06-12","data_fim_campanha":null,"titulo":"Range Rover Vogue, Range Rover Sport e Discovery Sport","fornecedor":"Jaguar e Land Rover Brasil Importação e Comércio de Veículos LTDA.","tipo_risco":"Cortes\/Ferimentos","pais_origem":"Reino Unido","produto":"Range Rover Vogue, Range Rover Sport e Discovery Sport","total_afetado":"50","total_atendido":"35"},
{"id":"61","data_inicio":"2017-07-10","data_fim_campanha":null,"titulo":"Jaguar F-Pace","fornecedor":"Jaguar e Land Rover Brasil Importação e Comércio de Veículos LTDA.","tipo_risco":"Fogo","pais_origem":"Reino Unido","produto":"Jaguar F-Pace","total_afetado":"14","total_atendido":"0"},
{"id":"62","data_inicio":"2017-01-19","data_fim_campanha":null,"titulo":"GLE 450 AMG, GLE 63 AMG, GLE 63 AMG Coupé, GL 63 AMG, GLS 63 AMG e GLE 400 Coupé","fornecedor":"MERCEDES-BENZ DO BRASIL LTDA.","tipo_risco":"Não funcionamento adequado do produto","pais_origem":"Alemanha","produto":"Mercedes-Benz, Classes GLE 450 AMG, GLE 63 AMG, GLE 63 AMG Coupé, GL 63 AMG, GLS 63 AMG e GLE 400 Coupé","total_afetado":"186","total_atendido":"0"},
{"id":"63","data_inicio":"2017-02-16","data_fim_campanha":null,"titulo":"Mercedes-Benz Classe ML 350 Sport Diesel - Parafusos dos eixos dianteiro e traseiro não terem sido montados corretamente.","fornecedor":"MERCEDES-BENZ DO BRASIL LTDA.","tipo_risco":"Perda de controle","pais_origem":"Brasil","produto":"Mercedes-Benz Classe ML 350 Sport Diesel","total_afetado":"1","total_atendido":"0"},
{"id":"64","data_inicio":"2017-03-09","data_fim_campanha":null,"titulo":"Mercedes-Benz, Classe E 250, modelos 2015 e 2016,  em razão da possibilidade de falha na solda dos contatos elétricos do módulo de assistência da direção.","fornecedor":"MERCEDES-BENZ DO BRASIL LTDA.","tipo_risco":"Perda de controle","pais_origem":"Brasil","produto":"Mercedes-Benz, Classe E 250","total_afetado":"2","total_atendido":"0"},
{"id":"65","data_inicio":"2017-04-25","data_fim_campanha":null,"titulo":"VITO Furgão, modelo 111","fornecedor":"MERCEDES-BENZ DO BRASIL LTDA.","tipo_risco":"Perda de controle","pais_origem":"Brasil","produto":"VITO Furgão","total_afetado":"307","total_atendido":"0"},
{"id":"66","data_inicio":"2017-05-11","data_fim_campanha":null,"titulo":"Mercedes-Benz Classe C 180 Coupé","fornecedor":"MERCEDES-BENZ DO BRASIL LTDA.","tipo_risco":"Cortes\/Ferimentos","pais_origem":"Alemanha","produto":"Mercedes-Benz Classe C 180 Coupé","total_afetado":"1","total_atendido":"0"},
{"id":"67","data_inicio":"2017-06-09","data_fim_campanha":null,"titulo":"Mercedes-Benz Classe CLA 200","fornecedor":"MERCEDES-BENZ DO BRASIL LTDA.","tipo_risco":"Cortes\/Ferimentos","pais_origem":"Alemanha","produto":"Mercedes-Benz Classe CLA 200","total_afetado":"1","total_atendido":"0"},
{"id":"68","data_inicio":"2017-06-21","data_fim_campanha":null,"titulo":"Mercedes-Benz Classe SLK 300, SLC 300 e SLC 43 AMG","fornecedor":"MERCEDES-BENZ DO BRASIL LTDA.","tipo_risco":"Queimaduras","pais_origem":"Alemanha","produto":"Mercedes-Benz Classe SLK 300, SLC 300 e SLC 43 AMG","total_afetado":"256","total_atendido":"0"},
{"id":"69","data_inicio":"2017-06-30","data_fim_campanha":null,"titulo":"Mercedes-Benz Classes A200, B200 e CLA200","fornecedor":"MERCEDES-BENZ DO BRASIL LTDA.","tipo_risco":"Cortes\/Ferimentos","pais_origem":"Alemanha","produto":"Mercedes-Benz Classes A200, B200 e CLA200","total_afetado":"1552","total_atendido":"0"},
{"id":"70","data_inicio":"2017-07-03","data_fim_campanha":null,"titulo":"Mercedes-Benz Classe G 63 AMG","fornecedor":"MERCEDES-BENZ DO BRASIL LTDA.","tipo_risco":"Cortes\/Ferimentos","pais_origem":"Alemanha","produto":"Mercedes-Benz Classe G 63 AMG","total_afetado":"29","total_atendido":"0"},
{"id":"71","data_inicio":"2017-07-04","data_fim_campanha":null,"titulo":"Mercedes-Benz Classe E 250","fornecedor":"MERCEDES-BENZ DO BRASIL LTDA.","tipo_risco":"Cortes\/Ferimentos","pais_origem":"Alemanha","produto":"Mercedes-Benz Classe E 250","total_afetado":"6","total_atendido":"0"},
{"id":"72","data_inicio":"2017-07-10","data_fim_campanha":null,"titulo":"Mercedes-Benz, modelos Extrapesados, Cavalos Mecânicos 6x4 2644, 2646, 2651 e 2655","fornecedor":"MERCEDES-BENZ DO BRASIL LTDA.","tipo_risco":"Cortes\/Ferimentos","pais_origem":"Brasil","produto":"Mercedes-Benz, Cavalos Mecânicos 6x4 2644, 2646, 2651 e 2655","total_afetado":"1581","total_atendido":"0"},
{"id":"73","data_inicio":"2017-07-17","data_fim_campanha":null,"titulo":"Classe A 250, CLA 200, CLA 250 E GLA 250","fornecedor":"MERCEDES-BENZ DO BRASIL LTDA.","tipo_risco":"Cortes\/Ferimentos","pais_origem":"Alemanha","produto":"MB Classe A 250, CLA 200, CLA 250 E GLA 250","total_afetado":"9","total_atendido":"0"},
{"id":"74","data_inicio":"2017-09-08","data_fim_campanha":null,"titulo":"Mercedes-Benz Classes GL, GLE e GLS","fornecedor":"MERCEDES-BENZ DO BRASIL LTDA.","tipo_risco":"Cortes\/Ferimentos","pais_origem":"Estados Unidos","produto":"Mercedes-Benz Classes GL, GLE e GLS","total_afetado":"521","total_atendido":"0"},
{"id":"75","data_inicio":"2017-09-14","data_fim_campanha":null,"titulo":"Classes A, B, C, E, CLA, GLA, GLC","fornecedor":"MERCEDES-BENZ DO BRASIL LTDA.","tipo_risco":"Fogo","pais_origem":"Brasil","produto":"Mercedes-benz classes A, B, C, E, CLA, GLA e GLC.","total_afetado":"14401","total_atendido":"0"},
{"id":"76","data_inicio":"2017-12-08","data_fim_campanha":null,"titulo":"MB, classes B ,C e GLA","fornecedor":"MERCEDES-BENZ DO BRASIL LTDA.","tipo_risco":"Fogo","pais_origem":"Hungria","produto":"MB, classes B ,C e GLA ","total_afetado":"3458","total_atendido":"0"},
{"id":"77","data_inicio":"2017-02-01","data_fim_campanha":null,"titulo":"Honda GL 1800 Gold Wing","fornecedor":"Moto Honda da Amazônia Ltda.","tipo_risco":"Não funcionamento adequado do produto","pais_origem":"Japão","produto":"Honda GL 1800 Gold Wing","total_afetado":"80","total_atendido":"41"},
{"id":"78","data_inicio":"2017-09-25","data_fim_campanha":null,"titulo":"Honda CRF 450R","fornecedor":"Moto Honda da Amazônia Ltda.","tipo_risco":"Cortes\/Ferimentos","pais_origem":"Japão","produto":"Honda CRF 450R","total_afetado":"220","total_atendido":"23"},
{"id":"79","data_inicio":"2017-03-13","data_fim_campanha":null,"titulo":"Carrinhos de passeio com bebê conforto, marca Britax, modelos Travel System B-Agile Brazil Neon Black e Chilli Pepper; e dos Carrinhos de bebê B-Agile Brazil Fóssil Brown, Chilli Pepper e Neon Black","fornecedor":"NEW TOYS COMÉRCIO DISTRIBUIÇÃO E IMPORTAÇÃO LTDA. ","tipo_risco":"Queda","pais_origem":"Brasil","produto":"Carrinhos de passeio com bebê conforto Travel System B-Agile Brazil","total_afetado":"964","total_atendido":"70"},
{"id":"80","data_inicio":"2017-07-28","data_fim_campanha":null,"titulo":"Nissan Frontier, Livina, Livina X-Gear, Grand Livina, Tiida e Tiida Sedan","fornecedor":"Nissan do Brasil Automóveis Ltda.","tipo_risco":"Cortes\/Ferimentos","pais_origem":"Brasil","produto":"Tiida | Tiida Sedan | Livina | Grand Livina | Livina X Gear | Frontier","total_afetado":"197155","total_atendido":"0"},
{"id":"81","data_inicio":"2017-02-03","data_fim_campanha":null,"titulo":"Citroën, modelos C4 Lounge 2.0 Flex","fornecedor":"Peugeot Citroen do Brasil Automoveis LTDA","tipo_risco":"Fogo","pais_origem":"Argentina","produto":"Citroën C4 Lounge","total_afetado":"7752","total_atendido":"0"},
{"id":"82","data_inicio":"2017-02-21","data_fim_campanha":null,"titulo":"Motocicletas Indian","fornecedor":"POLARIS DO BRASIL IMPORTACAO E COMERCIO DE VEICULOS E MOTOCICLETAS LTDA. ","tipo_risco":"Fogo","pais_origem":"Brasil","produto":"Chief Classic, Chief Vintage, Springfield, Chieftain e Roadmaster","total_afetado":"148","total_atendido":"0"},
{"id":"83","data_inicio":"2017-03-22","data_fim_campanha":null,"titulo":"Sportsman 570 Touring","fornecedor":"POLARIS DO BRASIL IMPORTACAO E COMERCIO DE VEICULOS E MOTOCICLETAS LTDA. ","tipo_risco":"Fogo","pais_origem":"Estados Unidos","produto":"Sportsman 570 Touring","total_afetado":"305","total_atendido":"39"},
{"id":"84","data_inicio":"2017-03-28","data_fim_campanha":null,"titulo":"RZR S 900 e RZR XP 1000","fornecedor":"POLARIS DO BRASIL IMPORTACAO E COMERCIO DE VEICULOS E MOTOCICLETAS LTDA. ","tipo_risco":"Fogo","pais_origem":"Estados Unidos","produto":"RZR S 900 e RZR XP 1000","total_afetado":"68","total_atendido":"6"},
{"id":"85","data_inicio":"2017-05-15","data_fim_campanha":null,"titulo":"Sportsman Touring 1000","fornecedor":"POLARIS DO BRASIL IMPORTACAO E COMERCIO DE VEICULOS E MOTOCICLETAS LTDA. ","tipo_risco":"Fogo","pais_origem":"Estados Unidos","produto":"Sportsman Touring 1000","total_afetado":"10","total_atendido":"3"},
{"id":"86","data_inicio":"2017-09-01","data_fim_campanha":null,"titulo":"Sportsman 570","fornecedor":"POLARIS DO BRASIL IMPORTACAO E COMERCIO DE VEICULOS E MOTOCICLETAS LTDA. ","tipo_risco":"Fogo","pais_origem":"Estados Unidos","produto":"Sportsman 570","total_afetado":"481","total_atendido":"28"},
{"id":"87","data_inicio":"2017-03-01","data_fim_campanha":null,"titulo":"911 Carrera (991), 911 Carrera S (991), 911 Carrera 4 (991), 911 Carrera 4S (991), 911 Targa 4 (991), 911 Targa 4S (991), 718 Boxster (982), 718 Boxster S (982), 718 Cayman (982) e 718 Cayman S (982),","fornecedor":"PORSCHE BRASIL IMPORTADORA DE VEÍCULOS LTDA.","tipo_risco":"Cortes\/Ferimentos","pais_origem":"Alemanha","produto":"911 Carrera, 911 Carrera S, 911 Carrera 4, 911 Carrera 4S, 911 Targa 4, 911 Targa 4S, 718 Boxster, 718 Boxster S, 718 Cayman e 718 Cayman S","total_afetado":"73","total_atendido":"0"},
{"id":"88","data_inicio":"2017-05-01","data_fim_campanha":null,"titulo":"Modelo Boxster 718","fornecedor":"PORSCHE BRASIL IMPORTADORA DE VEÍCULOS LTDA.","tipo_risco":"Cortes\/Ferimentos","pais_origem":"Alemanha","produto":"Porsche Boxster 718","total_afetado":"1","total_atendido":"0"},
{"id":"89","data_inicio":"2017-01-03","data_fim_campanha":null,"titulo":"Baterias dos notebooks da marca Positivo, modelos Positivo Premium XS4210; XS7210; XS8320; XS7205; XS7410; XS7330 e XS8410; e Positivo Premium TV XS3210 e XS3010","fornecedor":"Positivo Informática S\/A","tipo_risco":"Incêndio","pais_origem":"Brasil","produto":"Baterias dos notebooks Positivo, modelos Positivo Premium e Positivo Premium TV","total_afetado":"9719","total_atendido":"418"},
{"id":"90","data_inicio":"2017-01-26","data_fim_campanha":null,"titulo":"Renault Sandero e Duster","fornecedor":"Renault Do Brasil S.A.","tipo_risco":"Cortes\/Ferimentos","pais_origem":"Brasil","produto":"Renault Sandero e Duster","total_afetado":"3820","total_atendido":"1778"},
{"id":"91","data_inicio":"2017-02-23","data_fim_campanha":null,"titulo":"Renault Novo Sandero, Novo Logan, Novo Duster e Oroch","fornecedor":"Renault Do Brasil S.A.","tipo_risco":"Cortes\/Ferimentos","pais_origem":"Brasil","produto":"Renault Sandero, Logan, Duster (novos) e Oroch","total_afetado":"24814","total_atendido":"19559"},
{"id":"92","data_inicio":"2017-04-03","data_fim_campanha":null,"titulo":"Suzuki Grand Vitara","fornecedor":"SVB Automotores do Brasil S.A ","tipo_risco":"Cortes\/Ferimentos","pais_origem":"Japão","produto":"Suzuki Grand Vitara, modelos 2008 a 2013","total_afetado":"4741","total_atendido":"2693"},
{"id":"93","data_inicio":"2017-01-19","data_fim_campanha":null,"titulo":"Toyota, marca Lexus, modelo IS 300","fornecedor":"TOYOTA DO BRASIL LTDA","tipo_risco":"Cortes\/Ferimentos","pais_origem":"Japão","produto":"Lexus","total_afetado":"26","total_atendido":"20"},
{"id":"94","data_inicio":"2017-04-04","data_fim_campanha":null,"titulo":"Toyota Corolla","fornecedor":"TOYOTA DO BRASIL LTDA","tipo_risco":"Cortes\/Ferimentos","pais_origem":"Brasil","produto":"Toyota Corolla","total_afetado":"223518","total_atendido":"89981"},
{"id":"95","data_inicio":"2017-04-04","data_fim_campanha":null,"titulo":"Toyota Etios (airbag do lado do motorista e passageiro)","fornecedor":"TOYOTA DO BRASIL LTDA","tipo_risco":"Cortes\/Ferimentos","pais_origem":"Japão","produto":"Toyota Etios, fabricados entre agosto de 2012 e dezembro de 2014 | Toyota Etios, fabricados entre janeiro e dezembro de 2014","total_afetado":"162558","total_atendido":"86389"},
{"id":"96","data_inicio":"2017-06-19","data_fim_campanha":null,"titulo":"Toyota Hilux e Sw4","fornecedor":"TOYOTA DO BRASIL LTDA","tipo_risco":"Cortes\/Ferimentos","pais_origem":"Japão","produto":"Hilux e Sw4","total_afetado":"176866","total_atendido":"0"},
{"id":"97","data_inicio":"2017-06-19","data_fim_campanha":null,"titulo":"Toyota Corolla 2016","fornecedor":"TOYOTA DO BRASIL LTDA","tipo_risco":"Cortes\/Ferimentos","pais_origem":"Brasil","produto":"Toyota Corolla","total_afetado":"9890","total_atendido":"7163"},
{"id":"98","data_inicio":"2017-08-16","data_fim_campanha":null,"titulo":"Corolla XRS","fornecedor":"TOYOTA DO BRASIL LTDA","tipo_risco":"Cortes\/Ferimentos","pais_origem":"Japão","produto":"Corolla XRS","total_afetado":"456","total_atendido":"122"},
{"id":"99","data_inicio":"2017-03-21","data_fim_campanha":null,"titulo":"Bonneville T120 e Bonneville T120 - Black","fornecedor":"TRIUMPH - Fabricação de Motocicletas de Manaus Ltda.","tipo_risco":"Queda","pais_origem":"Brasil","produto":"Motocicletas Bonneville T120 | Bonneville T120 Black","total_afetado":"84","total_atendido":"0"},
{"id":"100","data_inicio":"2017-08-21","data_fim_campanha":null,"titulo":"Street Cup","fornecedor":"TRIUMPH - Fabricação de Motocicletas de Manaus Ltda.","tipo_risco":"Cortes\/Ferimentos","pais_origem":"Brasil","produto":"Street Cup","total_afetado":"24","total_atendido":"0"},
{"id":"101","data_inicio":"2017-03-07","data_fim_campanha":null,"titulo":"Jetta, Jetta Variant e Eos","fornecedor":"VOLKSWAGEN DO BRASIL INDÚSTRIA DE VEÍCULOS AUTOMOTORES LTDA.","tipo_risco":"Cortes\/Ferimentos","pais_origem":"Brasil","produto":"Jetta, Jetta Variant e Eos","total_afetado":"7182","total_atendido":"2007"},
{"id":"102","data_inicio":"2017-04-12","data_fim_campanha":null,"titulo":"Passat e Golf Variant","fornecedor":"VOLKSWAGEN DO BRASIL INDÚSTRIA DE VEÍCULOS AUTOMOTORES LTDA.","tipo_risco":"Cortes\/Ferimentos","pais_origem":"Brasil","produto":"Passat e Golf Variant","total_afetado":"398","total_atendido":"342"},
{"id":"103","data_inicio":"2017-04-12","data_fim_campanha":null,"titulo":"Amarok e Passat","fornecedor":"VOLKSWAGEN DO BRASIL INDÚSTRIA DE VEÍCULOS AUTOMOTORES LTDA.","tipo_risco":"Cortes\/Ferimentos","pais_origem":"Brasil","produto":"Amarok e Passat","total_afetado":"47","total_atendido":"44"},
{"id":"104","data_inicio":"2017-05-10","data_fim_campanha":null,"titulo":"Up!, novo Gol, novo Voyage, nova Saveiro, Fox, CrossFox, Spacefox e Space Cross","fornecedor":"VOLKSWAGEN DO BRASIL INDÚSTRIA DE VEÍCULOS AUTOMOTORES LTDA.","tipo_risco":"Cortes\/Ferimentos","pais_origem":"Brasil","produto":"Up!, novo Gol, novo Voyage, nova Saveiro, Fox, CrossFox, Spacefox e Space Cross","total_afetado":"54170","total_atendido":"30187"},
{"id":"105","data_inicio":"2017-01-16","data_fim_campanha":null,"titulo":"Volvo, modelos V40, V40 CC, S60, V60 e XC60, ano\/modelo 2017","fornecedor":"Volvo Car Brasil Importação e Comércio de Veículos Ltda.","tipo_risco":"Cortes\/Ferimentos","pais_origem":"Brasil","produto":"Volvo V40 | V40CC | S60 | V60 | XC60","total_afetado":"95","total_atendido":"0"},
{"id":"106","data_inicio":"2017-03-15","data_fim_campanha":null,"titulo":"VOLVO XC90","fornecedor":"Volvo Car Brasil Importação e Comércio de Veículos Ltda.","tipo_risco":"Cortes\/Ferimentos","pais_origem":"Suécia","produto":"Volvo XC90","total_afetado":"4","total_atendido":"2"},
{"id":"107","data_inicio":"2017-03-15","data_fim_campanha":null,"titulo":"VOLVO XC90 modelos 2017","fornecedor":"Volvo Car Brasil Importação e Comércio de Veículos Ltda.","tipo_risco":"Cortes\/Ferimentos","pais_origem":"Suécia","produto":"Volvo XC90","total_afetado":"29","total_atendido":"21"},
{"id":"108","data_inicio":"2017-07-05","data_fim_campanha":null,"titulo":"VOLVO XC90 ano\/modelo 2017","fornecedor":"Volvo Car Brasil Importação e Comércio de Veículos Ltda.","tipo_risco":"Cortes\/Ferimentos","pais_origem":"Suécia","produto":"Volvo XC90","total_afetado":"34","total_atendido":"0"},
{"id":"109","data_inicio":"2017-03-03","data_fim_campanha":null,"titulo":"Yamaha, FAZER 250, LANDER 250, TÉNÉRÉ 250, R3 e MT03","fornecedor":"YAMAHA MOTOR DA AMAZÔNIA LTDA.","tipo_risco":"Cortes\/Ferimentos","pais_origem":"Brasil","produto":"Yamaha FAZER 250, LANDER 250, TÉNÉRÉ 250, R3 e MT03.","total_afetado":"40471","total_atendido":"15637"},
{"id":"110","data_inicio":"2017-03-03","data_fim_campanha":null,"titulo":"Yamaha R3 e MT03","fornecedor":"YAMAHA MOTOR DA AMAZÔNIA LTDA.","tipo_risco":"Fogo","pais_origem":"Brasil","produto":"Yamaha R3 e MT03","total_afetado":"9513","total_atendido":"5215"},
{"id":"111","data_inicio":"2017-04-10","data_fim_campanha":null,"titulo":"Yamaha MT-09 e MT-09 Tracer.","fornecedor":"YAMAHA MOTOR DA AMAZÔNIA LTDA.","tipo_risco":"Queda","pais_origem":"Brasil","produto":"Yamaha MT-09 e MT-09 Tracer","total_afetado":"2770","total_atendido":"718"}
]
}
]
